<?xml version="1.0" encoding="utf-8" ?>

<roles>
    <role name="sysadmin">
        <default-url><![CDATA[~/account/sysadmin/]]></default-url>
    </role>
    <role name="siteadmin">
        <default-url><![CDATA[~/account/siteadmin/]]></default-url>
    </role>
    <role name="editor">
        <default-url><![CDATA[~/account/editor/]]></default-url>
    </role>
    <role name="guest">
        <default-url><![CDATA[~/thanh-vien/thong-tin-tai-khoan.aspx]]></default-url>
    </role>
</roles>